oboyu/__init__.py
oboyu/__main__.py
oboyu/py.typed
oboyu/adapters/__init__.py
oboyu/adapters/config/__init__.py
oboyu/adapters/config/configuration_adapter.py
oboyu/adapters/database/__init__.py
oboyu/adapters/database/duckdb_search_repository.py
oboyu/adapters/embedding/__init__.py
oboyu/adapters/embedding/huggingface_embedding_service.py
oboyu/adapters/entity_deduplication/__init__.py
oboyu/adapters/entity_deduplication/edc_deduplication_service.py
oboyu/adapters/filesystem/__init__.py
oboyu/adapters/filesystem/local_filesystem_adapter.py
oboyu/adapters/graphrag/__init__.py
oboyu/adapters/graphrag/chunk_retrieval.py
oboyu/adapters/graphrag/entity_analysis.py
oboyu/adapters/graphrag/oboyu_graphrag_service.py
oboyu/adapters/graphrag/query_expansion.py
oboyu/adapters/kg_extraction/__init__.py
oboyu/adapters/kg_extraction/llm_kg_extraction_service.py
oboyu/adapters/kg_repositories/__init__.py
oboyu/adapters/kg_repositories/base.py
oboyu/adapters/kg_repositories/duckdb_kg_repository.py
oboyu/adapters/property_graph/__init__.py
oboyu/adapters/property_graph/duckpgq_property_graph_service.py
oboyu/application/__init__.py
oboyu/application/container.py
oboyu/application/factory.py
oboyu/application/enrichment/__init__.py
oboyu/application/enrichment/enrichment_service.py
oboyu/application/enrichment/extraction_strategies.py
oboyu/application/enrichment/protocols.py
oboyu/application/indexing/__init__.py
oboyu/application/indexing/indexing_service.py
oboyu/application/kg/__init__.py
oboyu/application/kg/kg_service.py
oboyu/application/management/__init__.py
oboyu/application/searching/__init__.py
oboyu/application/searching/search_service.py
oboyu/cli/__init__.py
oboyu/cli/__main__.py
oboyu/cli/base.py
oboyu/cli/build_kg.py
oboyu/cli/clear.py
oboyu/cli/common_options.py
oboyu/cli/config.py
oboyu/cli/deduplicate.py
oboyu/cli/enrich.py
oboyu/cli/formatters.py
oboyu/cli/hierarchical_logger.py
oboyu/cli/index.py
oboyu/cli/index_config.py
oboyu/cli/main.py
oboyu/cli/mcp.py
oboyu-0.1.0a4.dist-info/METADATA
oboyu-0.1.0a4.dist-info/WHEEL
oboyu-0.1.0a4.dist-info/entry_points.txt
oboyu-0.1.0a4.dist-info/licenses/LICENSE.md
oboyu-0.1.0a4.dist-info/RECORD
