Metadata-Version: 2.4
Name: oboyu
Version: 0.1.0a4
Summary: A Japanese-enhanced semantic search system for your local documents.
Author-email: sonesuke <iamsonesuke@gmail.com>
License: MIT
License-File: LICENSE.md
Keywords: document-search,japanese,semantic-search,text-processing,vector-search
Classifier: Development Status :: 4 - Beta
Classifier: Intended Audience :: Developers
Classifier: License :: OSI Approved :: MIT License
Classifier: Natural Language :: Japanese
Classifier: Operating System :: OS Independent
Classifier: Programming Language :: Python :: 3.13
Classifier: Topic :: Text Processing :: Indexing
Requires-Python: >=3.13
Requires-Dist: chardet>=5.2.0
Requires-Dist: charset-normalizer>=3.4.2
Requires-Dist: cryptography>=45.0.4
Requires-Dist: duckdb>=1.3.0
Requires-Dist: fasttext>=0.9.3
Requires-Dist: ftfy>=6.1.0
Requires-Dist: fugashi>=1.4.3
Requires-Dist: gitignore-parser>=0.1.12
Requires-Dist: huggingface-hub>=0.27.0
Requires-Dist: instructor>=1.8.0
Requires-Dist: jaconv>=0.4.0
Requires-Dist: llama-cpp-python>=0.3.9
Requires-Dist: mcp[cli]>=1.9.2
Requires-Dist: mojimoji>=0.0.12
Requires-Dist: neologdn>=0.5.2
Requires-Dist: numpy>=2.2.6
Requires-Dist: onnx>=1.18.0
Requires-Dist: onnxruntime>=1.22.0
Requires-Dist: optimum>=1.25.3
Requires-Dist: pandas>=2.2.3
Requires-Dist: protobuf>=6.31.1
Requires-Dist: pydantic>=2.11.5
Requires-Dist: pymupdf4llm>=0.0.25
Requires-Dist: python-frontmatter>=1.1.0
Requires-Dist: pyyaml>=6.0.2
Requires-Dist: rich<14.0.0,>=13.7.0
Requires-Dist: sentence-transformers>=4.1.0
Requires-Dist: sentencepiece>=0.2.0
Requires-Dist: torch>=2.7.0
Requires-Dist: transformers>=4.52.4
Requires-Dist: typer>=0.16.0
Requires-Dist: unidic-lite>=1.0.8
Requires-Dist: xdg-base-dirs>=6.0.2
